{
  "name": "base",
  "benchmarks": {
    "bench_hmr_to_commit/Next.js 12 webpack SSR/100 modules": {
      "baseline": "base",
      "fullname": "base/bench_hmr_to_commit/Next.js 12 webpack SSR/100 modules",
      "criterion_benchmark_v1": {
        "group_id": "bench_hmr_to_commit",
        "function_id": "Next.js 12 webpack SSR",
        "value_str": "100 modules",
        "throughput": null,
        "full_id": "bench_hmr_to_commit/Next.js 12 webpack SSR/100 modules",
        "directory_name": "bench_hmr_to_commit/Next.js 12 webpack SSR/100 modules"
      },
      "criterion_estimates_v1": {
        "mean": {
          "confidence_interval": {
            "confidence_level": 0.95,
            "lower_bound": 74396640.22928572,
            "upper_bound": 75487777.34778486
          },
          "point_estimate": 74988862.33493198,
          "standard_error": 280581.79972270236
        },
        "median": {
          "confidence_interval": {
            "confidence_level": 0.95,
            "lower_bound": 74557663.23214287,
            "upper_bound": 75688058.04761904
          },
          "point_estimate": 75144172.84013605,
          "standard_error": 313112.2940740009
        },
        "median_abs_dev": {
          "confidence_interval": {
            "confidence_level": 0.95,
            "lower_bound": 240425.64823159095,
            "upper_bound": 1378278.6444806426
          },
          "point_estimate": 790883.4602590144,
          "standard_error": 291787.2370122964
        },
        "slope": {
          "confidence_interval": {
            "confidence_level": 0.95,
            "lower_bound": 74351592.2598535,
            "upper_bound": 75207501.98514548
          },
          "point_estimate": 74804179.86679035,
          "standard_error": 212905.4054848271
        },
        "std_dev": {
          "confidence_interval": {
            "confidence_level": 0.95,
            "lower_bound": 416850.1915316426,
            "upper_bound": 1294433.736125169
          },
          "point_estimate": 938277.2233313324,
          "standard_error": 253890.6692554751
        }
      }
    },
    "bench_hmr_to_commit/Next.js 12 webpack SSR/1000 modules": {
      "baseline": "base",
      "fullname": "base/bench_hmr_to_commit/Next.js 12 webpack SSR/1000 modules",
      "criterion_benchmark_v1": {
        "group_id": "bench_hmr_to_commit",
        "function_id": "Next.js 12 webpack SSR",
        "value_str": "1000 modules",
        "throughput": null,
        "full_id": "bench_hmr_to_commit/Next.js 12 webpack SSR/1000 modules",
        "directory_name": "bench_hmr_to_commit/Next.js 12 webpack SSR/1000 modules"
      },
      "criterion_estimates_v1": {
        "mean": {
          "confidence_interval": {
            "confidence_level": 0.95,
            "lower_bound": 145248339.09297165,
            "upper_bound": 162675705.1342222
          },
          "point_estimate": 153119954.88100794,
          "standard_error": 4493327.832676278
        },
        "median": {
          "confidence_interval": {
            "confidence_level": 0.95,
            "lower_bound": 142371336.34,
            "upper_bound": 163943329.3
          },
          "point_estimate": 147396575.49,
          "standard_error": 4892663.259589557
        },
        "median_abs_dev": {
          "confidence_interval": {
            "confidence_level": 0.95,
            "lower_bound": 1930069.9045711125,
            "upper_bound": 22303569.29091248
          },
          "point_estimate": 9812834.834284848,
          "standard_error": 5160627.741743401
        },
        "slope": {
          "confidence_interval": {
            "confidence_level": 0.95,
            "lower_bound": 142401951.92927104,
            "upper_bound": 149062711.5382353
          },
          "point_estimate": 144638118.92623377,
          "standard_error": 1705324.1642544903
        },
        "std_dev": {
          "confidence_interval": {
            "confidence_level": 0.95,
            "lower_bound": 4832221.630722467,
            "upper_bound": 19463426.011772875
          },
          "point_estimate": 14955389.3576466,
          "standard_error": 3847883.975968635
        }
      }
    },
    "bench_hmr_to_commit/Next.js 12 webpack SSR/500 modules": {
      "baseline": "base",
      "fullname": "base/bench_hmr_to_commit/Next.js 12 webpack SSR/500 modules",
      "criterion_benchmark_v1": {
        "group_id": "bench_hmr_to_commit",
        "function_id": "Next.js 12 webpack SSR",
        "value_str": "500 modules",
        "throughput": null,
        "full_id": "bench_hmr_to_commit/Next.js 12 webpack SSR/500 modules",
        "directory_name": "bench_hmr_to_commit/Next.js 12 webpack SSR/500 modules"
      },
      "criterion_estimates_v1": {
        "mean": {
          "confidence_interval": {
            "confidence_level": 0.95,
            "lower_bound": 108874737.55375,
            "upper_bound": 119146490.74295
          },
          "point_estimate": 113437994.63533331,
          "standard_error": 2663242.4652740066
        },
        "median": {
          "confidence_interval": {
            "confidence_level": 0.95,
            "lower_bound": 107691707.51,
            "upper_bound": 117687085.475
          },
          "point_estimate": 108742831.025,
          "standard_error": 2954123.5974890064
        },
        "median_abs_dev": {
          "confidence_interval": {
            "confidence_level": 0.95,
            "lower_bound": 478163.1026708991,
            "upper_bound": 13260751.412144594
          },
          "point_estimate": 2402672.8265630417,
          "standard_error": 3495678.7302645375
        },
        "slope": {
          "confidence_interval": {
            "confidence_level": 0.95,
            "lower_bound": 107597249.29463255,
            "upper_bound": 111112345.7015481
          },
          "point_estimate": 108819918.25662336,
          "standard_error": 924008.012140405
        },
        "std_dev": {
          "confidence_interval": {
            "confidence_level": 0.95,
            "lower_bound": 2175459.2804068024,
            "upper_bound": 12121902.037046518
          },
          "point_estimate": 8881365.076902408,
          "standard_error": 2561760.229742836
        }
      }
    },
    "bench_hmr_to_eval/Next.js 12 webpack SSR/100 modules": {
      "baseline": "base",
      "fullname": "base/bench_hmr_to_eval/Next.js 12 webpack SSR/100 modules",
      "criterion_benchmark_v1": {
        "group_id": "bench_hmr_to_eval",
        "function_id": "Next.js 12 webpack SSR",
        "value_str": "100 modules",
        "throughput": null,
        "full_id": "bench_hmr_to_eval/Next.js 12 webpack SSR/100 modules",
        "directory_name": "bench_hmr_to_eval/Next.js 12 webpack SSR/100 modules"
      },
      "criterion_estimates_v1": {
        "mean": {
          "confidence_interval": {
            "confidence_level": 0.95,
            "lower_bound": 41722157.60294643,
            "upper_bound": 43404878.19237723
          },
          "point_estimate": 42521953.22595238,
          "standard_error": 430370.5677990392
        },
        "median": {
          "confidence_interval": {
            "confidence_level": 0.95,
            "lower_bound": 41482907.125,
            "upper_bound": 43555839.25
          },
          "point_estimate": 42253936.140625,
          "standard_error": 546519.5756207368
        },
        "median_abs_dev": {
          "confidence_interval": {
            "confidence_level": 0.95,
            "lower_bound": 327599.92330893874,
            "upper_bound": 2443481.387132032
          },
          "point_estimate": 1464164.941718377,
          "standard_error": 519080.4347117656
        },
        "slope": {
          "confidence_interval": {
            "confidence_level": 0.95,
            "lower_bound": 41074379.570592135,
            "upper_bound": 42546122.79060599
          },
          "point_estimate": 41622707.983766235,
          "standard_error": 377071.31152573007
        },
        "std_dev": {
          "confidence_interval": {
            "confidence_level": 0.95,
            "lower_bound": 739926.7095891656,
            "upper_bound": 1883207.1391070103
          },
          "point_estimate": 1433827.625819501,
          "standard_error": 304558.0517361442
        }
      }
    },
    "bench_hmr_to_eval/Next.js 12 webpack SSR/1000 modules": {
      "baseline": "base",
      "fullname": "base/bench_hmr_to_eval/Next.js 12 webpack SSR/1000 modules",
      "criterion_benchmark_v1": {
        "group_id": "bench_hmr_to_eval",
        "function_id": "Next.js 12 webpack SSR",
        "value_str": "1000 modules",
        "throughput": null,
        "full_id": "bench_hmr_to_eval/Next.js 12 webpack SSR/1000 modules",
        "directory_name": "bench_hmr_to_eval/Next.js 12 webpack SSR/1000 modules"
      },
      "criterion_estimates_v1": {
        "mean": {
          "confidence_interval": {
            "confidence_level": 0.95,
            "lower_bound": 115510603.71118252,
            "upper_bound": 131443838.17266668
          },
          "point_estimate": 122662496.37734129,
          "standard_error": 4093332.906665357
        },
        "median": {
          "confidence_interval": {
            "confidence_level": 0.95,
            "lower_bound": 113651979.06666666,
            "upper_bound": 129793082.26666668
          },
          "point_estimate": 115813526.08253968,
          "standard_error": 4527527.773644229
        },
        "median_abs_dev": {
          "confidence_interval": {
            "confidence_level": 0.95,
            "lower_bound": 432680.6113850432,
            "upper_bound": 20726089.63062503
          },
          "point_estimate": 5721949.874474912,
          "standard_error": 5149841.549147068
        },
        "slope": {
          "confidence_interval": {
            "confidence_level": 0.95,
            "lower_bound": 113259810.1769953,
            "upper_bound": 117850352.63790454
          },
          "point_estimate": 114862517.24155843,
          "standard_error": 1190928.331252758
        },
        "std_dev": {
          "confidence_interval": {
            "confidence_level": 0.95,
            "lower_bound": 3515291.236680545,
            "upper_bound": 18412096.557258155
          },
          "point_estimate": 13724030.050427957,
          "standard_error": 3736549.714789747
        }
      }
    },
    "bench_hmr_to_eval/Next.js 12 webpack SSR/500 modules": {
      "baseline": "base",
      "fullname": "base/bench_hmr_to_eval/Next.js 12 webpack SSR/500 modules",
      "criterion_benchmark_v1": {
        "group_id": "bench_hmr_to_eval",
        "function_id": "Next.js 12 webpack SSR",
        "value_str": "500 modules",
        "throughput": null,
        "full_id": "bench_hmr_to_eval/Next.js 12 webpack SSR/500 modules",
        "directory_name": "bench_hmr_to_eval/Next.js 12 webpack SSR/500 modules"
      },
      "criterion_estimates_v1": {
        "mean": {
          "confidence_interval": {
            "confidence_level": 0.95,
            "lower_bound": 72304880.14910716,
            "upper_bound": 81471893.24189551
          },
          "point_estimate": 76491215.71707013,
          "standard_error": 2358207.3798067826
        },
        "median": {
          "confidence_interval": {
            "confidence_level": 0.95,
            "lower_bound": 70804159.70208333,
            "upper_bound": 81472371.77777778
          },
          "point_estimate": 73286036.22916667,
          "standard_error": 2729125.52783585
        },
        "median_abs_dev": {
          "confidence_interval": {
            "confidence_level": 0.95,
            "lower_bound": 714399.6249643698,
            "upper_bound": 12317911.329121
          },
          "point_estimate": 4312798.067313782,
          "standard_error": 3060678.0024799216
        },
        "slope": {
          "confidence_interval": {
            "confidence_level": 0.95,
            "lower_bound": 70347538.70947176,
            "upper_bound": 74366526.71987057
          },
          "point_estimate": 71889632.26277056,
          "standard_error": 1022523.1750733628
        },
        "std_dev": {
          "confidence_interval": {
            "confidence_level": 0.95,
            "lower_bound": 2470093.376451116,
            "upper_bound": 10011869.300645022
          },
          "point_estimate": 7859444.186599501,
          "standard_error": 1824199.687408495
        }
      }
    },
    "bench_hydration/Next.js 12 webpack SSR/100 modules": {
      "baseline": "base",
      "fullname": "base/bench_hydration/Next.js 12 webpack SSR/100 modules",
      "criterion_benchmark_v1": {
        "group_id": "bench_hydration",
        "function_id": "Next.js 12 webpack SSR",
        "value_str": "100 modules",
        "throughput": null,
        "full_id": "bench_hydration/Next.js 12 webpack SSR/100 modules",
        "directory_name": "bench_hydration/Next.js 12 webpack SSR/100 modules"
      },
      "criterion_estimates_v1": {
        "mean": {
          "confidence_interval": {
            "confidence_level": 0.95,
            "lower_bound": 2823436724.48,
            "upper_bound": 2855473724.5675
          },
          "point_estimate": 2837916730.05,
          "standard_error": 8210947.036305549
        },
        "median": {
          "confidence_interval": {
            "confidence_level": 0.95,
            "lower_bound": 2819511651.0,
            "upper_bound": 2850689674.5
          },
          "point_estimate": 2833348752.75,
          "standard_error": 7525886.002771057
        },
        "median_abs_dev": {
          "confidence_interval": {
            "confidence_level": 0.95,
            "lower_bound": 4516634.813913703,
            "upper_bound": 38785821.99681401
          },
          "point_estimate": 23112268.410225213,
          "standard_error": 8602785.19595141
        },
        "slope": null,
        "std_dev": {
          "confidence_interval": {
            "confidence_level": 0.95,
            "lower_bound": 10953618.757466748,
            "upper_bound": 38423207.84183437
          },
          "point_estimate": 27428622.125839688,
          "standard_error": 7897138.649135424
        }
      }
    },
    "bench_hydration/Next.js 12 webpack SSR/1000 modules": {
      "baseline": "base",
      "fullname": "base/bench_hydration/Next.js 12 webpack SSR/1000 modules",
      "criterion_benchmark_v1": {
        "group_id": "bench_hydration",
        "function_id": "Next.js 12 webpack SSR",
        "value_str": "1000 modules",
        "throughput": null,
        "full_id": "bench_hydration/Next.js 12 webpack SSR/1000 modules",
        "directory_name": "bench_hydration/Next.js 12 webpack SSR/1000 modules"
      },
      "criterion_estimates_v1": {
        "mean": {
          "confidence_interval": {
            "confidence_level": 0.95,
            "lower_bound": 6955989502.6,
            "upper_bound": 7040859871.3
          },
          "point_estimate": 6997288945.4,
          "standard_error": 21764007.178892516
        },
        "median": {
          "confidence_interval": {
            "confidence_level": 0.95,
            "lower_bound": 6929213444.0,
            "upper_bound": 7059347163.5
          },
          "point_estimate": 6990987049.5,
          "standard_error": 34995198.769426614
        },
        "median_abs_dev": {
          "confidence_interval": {
            "confidence_level": 0.95,
            "lower_bound": 21149485.81032157,
            "upper_bound": 120240514.67080414
          },
          "point_estimate": 88968733.21318924,
          "standard_error": 25469604.973351493
        },
        "slope": null,
        "std_dev": {
          "confidence_interval": {
            "confidence_level": 0.95,
            "lower_bound": 44324809.68093929,
            "upper_bound": 87849599.98815188
          },
          "point_estimate": 72419323.51022266,
          "standard_error": 11151452.953711906
        }
      }
    },
    "bench_hydration/Next.js 12 webpack SSR/500 modules": {
      "baseline": "base",
      "fullname": "base/bench_hydration/Next.js 12 webpack SSR/500 modules",
      "criterion_benchmark_v1": {
        "group_id": "bench_hydration",
        "function_id": "Next.js 12 webpack SSR",
        "value_str": "500 modules",
        "throughput": null,
        "full_id": "bench_hydration/Next.js 12 webpack SSR/500 modules",
        "directory_name": "bench_hydration/Next.js 12 webpack SSR/500 modules"
      },
      "criterion_estimates_v1": {
        "mean": {
          "confidence_interval": {
            "confidence_level": 0.95,
            "lower_bound": 4821178359.9175,
            "upper_bound": 4869694497.743751
          },
          "point_estimate": 4844052534.45,
          "standard_error": 12459029.085151909
        },
        "median": {
          "confidence_interval": {
            "confidence_level": 0.95,
            "lower_bound": 4808149684.5,
            "upper_bound": 4866309081.25
          },
          "point_estimate": 4844814500.25,
          "standard_error": 16686778.129755097
        },
        "median_abs_dev": {
          "confidence_interval": {
            "confidence_level": 0.95,
            "lower_bound": 6288326.215159893,
            "upper_bound": 71825398.95359427
          },
          "point_estimate": 48675884.29618031,
          "standard_error": 16398705.142606989
        },
        "slope": null,
        "std_dev": {
          "confidence_interval": {
            "confidence_level": 0.95,
            "lower_bound": 21613765.101145335,
            "upper_bound": 55342292.87116072
          },
          "point_estimate": 41727195.749184705,
          "standard_error": 9373615.361624964
        }
      }
    },
    "bench_startup/Next.js 12 webpack SSR/100 modules": {
      "baseline": "base",
      "fullname": "base/bench_startup/Next.js 12 webpack SSR/100 modules",
      "criterion_benchmark_v1": {
        "group_id": "bench_startup",
        "function_id": "Next.js 12 webpack SSR",
        "value_str": "100 modules",
        "throughput": null,
        "full_id": "bench_startup/Next.js 12 webpack SSR/100 modules",
        "directory_name": "bench_startup/Next.js 12 webpack SSR/100 modules"
      },
      "criterion_estimates_v1": {
        "mean": {
          "confidence_interval": {
            "confidence_level": 0.95,
            "lower_bound": 2478221544.245,
            "upper_bound": 2512395542.8525
          },
          "point_estimate": 2494984251.5,
          "standard_error": 8751730.402961241
        },
        "median": {
          "confidence_interval": {
            "confidence_level": 0.95,
            "lower_bound": 2469494050.0,
            "upper_bound": 2522969825.5
          },
          "point_estimate": 2485201403.0,
          "standard_error": 17143024.770077072
        },
        "median_abs_dev": {
          "confidence_interval": {
            "confidence_level": 0.95,
            "lower_bound": 5481348.532086611,
            "upper_bound": 46317678.93989682
          },
          "point_estimate": 32193790.36614597,
          "standard_error": 11616490.014387084
        },
        "slope": null,
        "std_dev": {
          "confidence_interval": {
            "confidence_level": 0.95,
            "lower_bound": 18363091.53138483,
            "upper_bound": 34309883.09455249
          },
          "point_estimate": 29474355.675524283,
          "standard_error": 3936986.3615926057
        }
      }
    },
    "bench_startup/Next.js 12 webpack SSR/1000 modules": {
      "baseline": "base",
      "fullname": "base/bench_startup/Next.js 12 webpack SSR/1000 modules",
      "criterion_benchmark_v1": {
        "group_id": "bench_startup",
        "function_id": "Next.js 12 webpack SSR",
        "value_str": "1000 modules",
        "throughput": null,
        "full_id": "bench_startup/Next.js 12 webpack SSR/1000 modules",
        "directory_name": "bench_startup/Next.js 12 webpack SSR/1000 modules"
      },
      "criterion_estimates_v1": {
        "mean": {
          "confidence_interval": {
            "confidence_level": 0.95,
            "lower_bound": 5720698004.22,
            "upper_bound": 5781227839.3
          },
          "point_estimate": 5750797223.4,
          "standard_error": 15469110.691661453
        },
        "median": {
          "confidence_interval": {
            "confidence_level": 0.95,
            "lower_bound": 5712739886.5,
            "upper_bound": 5802251956.0
          },
          "point_estimate": 5736863080.5,
          "standard_error": 25687309.964381676
        },
        "median_abs_dev": {
          "confidence_interval": {
            "confidence_level": 0.95,
            "lower_bound": 9185569.71012354,
            "upper_bound": 88458649.14004505
          },
          "point_estimate": 64884912.963062525,
          "standard_error": 21952508.44113569
        },
        "slope": null,
        "std_dev": {
          "confidence_interval": {
            "confidence_level": 0.95,
            "lower_bound": 32443663.80822514,
            "upper_bound": 62770445.05559459
          },
          "point_estimate": 51619032.59390221,
          "standard_error": 7857414.939540507
        }
      }
    },
    "bench_startup/Next.js 12 webpack SSR/500 modules": {
      "baseline": "base",
      "fullname": "base/bench_startup/Next.js 12 webpack SSR/500 modules",
      "criterion_benchmark_v1": {
        "group_id": "bench_startup",
        "function_id": "Next.js 12 webpack SSR",
        "value_str": "500 modules",
        "throughput": null,
        "full_id": "bench_startup/Next.js 12 webpack SSR/500 modules",
        "directory_name": "bench_startup/Next.js 12 webpack SSR/500 modules"
      },
      "criterion_estimates_v1": {
        "mean": {
          "confidence_interval": {
            "confidence_level": 0.95,
            "lower_bound": 4032400846.3,
            "upper_bound": 4077175886.9675
          },
          "point_estimate": 4053784398.55,
          "standard_error": 11478084.143950578
        },
        "median": {
          "confidence_interval": {
            "confidence_level": 0.95,
            "lower_bound": 4020060310.5,
            "upper_bound": 4084734460.0
          },
          "point_estimate": 4041675193.25,
          "standard_error": 18576765.062157337
        },
        "median_abs_dev": {
          "confidence_interval": {
            "confidence_level": 0.95,
            "lower_bound": 7859852.16460973,
            "upper_bound": 64388547.01682478
          },
          "point_estimate": 41553057.04138577,
          "standard_error": 14650563.68410976
        },
        "slope": null,
        "std_dev": {
          "confidence_interval": {
            "confidence_level": 0.95,
            "lower_bound": 21733969.119691692,
            "upper_bound": 47212200.64344382
          },
          "point_estimate": 38265570.390276074,
          "standard_error": 6638780.027146699
        }
      }
    }
  }
}
